isage_refiner-0.1.0.2.dist-info/licenses/LICENSE
sage_refiner/__init__.py
sage_refiner/__init__.pyc
sage_refiner/_version.py
sage_refiner/_version.pyc
sage_refiner/config.pyc
sage_refiner/__pycache__/__init__.cpython-310.pyc
sage_refiner/__pycache__/__init__.cpython-311.pyc
sage_refiner/__pycache__/_version.cpython-310.pyc
sage_refiner/__pycache__/_version.cpython-311.pyc
sage_refiner/__pycache__/config.cpython-310.pyc
sage_refiner/__pycache__/config.cpython-311.pyc
sage_refiner/algorithms/__init__.py
sage_refiner/algorithms/__init__.pyc
sage_refiner/algorithms/EHPC/__init__.py
sage_refiner/algorithms/EHPC/__init__.pyc
sage_refiner/algorithms/EHPC/compressor.pyc
sage_refiner/algorithms/EHPC/config.pyc
sage_refiner/algorithms/EHPC/operator.pyc
sage_refiner/algorithms/EHPC/models/__init__.py
sage_refiner/algorithms/EHPC/models/__init__.pyc
sage_refiner/algorithms/EHPC/models/gemfilter/__init__.py
sage_refiner/algorithms/EHPC/models/gemfilter/__init__.pyc
sage_refiner/algorithms/EHPC/models/gemfilter/attention_mixin.pyc
sage_refiner/algorithms/EHPC/models/gemfilter/llama_select_attention.pyc
sage_refiner/algorithms/EHPC/models/gemfilter/mistral_select_attention.pyc
sage_refiner/algorithms/EHPC/models/gemfilter/model_loader.pyc
sage_refiner/algorithms/EHPC/models/gemfilter/utils.pyc
sage_refiner/algorithms/EHPC/probe/__init__.py
sage_refiner/algorithms/EHPC/probe/__init__.pyc
sage_refiner/algorithms/EHPC/scripts/__init__.py
sage_refiner/algorithms/EHPC/scripts/__init__.pyc
sage_refiner/algorithms/EHPC/scripts/find_heads.pyc
sage_refiner/algorithms/LongRefiner/__init__.py
sage_refiner/algorithms/LongRefiner/__init__.pyc
sage_refiner/algorithms/LongRefiner/compressor.pyc
sage_refiner/algorithms/LongRefiner/operator.pyc
sage_refiner/algorithms/LongRefiner/prompt_template.pyc
sage_refiner/algorithms/LongRefiner/task_instruction.pyc
sage_refiner/algorithms/LongRefiner/__pycache__/__init__.cpython-310.pyc
sage_refiner/algorithms/LongRefiner/__pycache__/__init__.cpython-311.pyc
isage_refiner-0.1.0.2.dist-info/METADATA
isage_refiner-0.1.0.2.dist-info/WHEEL
isage_refiner-0.1.0.2.dist-info/top_level.txt
isage_refiner-0.1.0.2.dist-info/RECORD
