Metadata-Version: 2.4
Name: isage-refiner
Version: 0.1.0.2
Summary: Intelligent context compression algorithms for LLM systems
Author-email: IntelliStream Team <shuhao_zhang@hust.edu.cn>
License: Apache-2.0
Project-URL: Homepage, https://github.com/intellistream/sageRefiner
Project-URL: Documentation, https://intellistream.github.io/SAGE/
Project-URL: Repository, https://github.com/intellistream/sageRefiner
Project-URL: Bug Tracker, https://github.com/intellistream/sageRefiner/issues
Keywords: rag,llm,compression,context,nlp,ai,ml
Classifier: Development Status :: 3 - Alpha
Classifier: Intended Audience :: Developers
Classifier: Intended Audience :: Science/Research
Classifier: License :: OSI Approved :: Apache Software License
Classifier: Programming Language :: Python :: 3
Classifier: Programming Language :: Python :: 3.11
Classifier: Programming Language :: Python :: 3.12
Classifier: Topic :: Scientific/Engineering :: Artificial Intelligence
Requires-Python: >=3.11
License-File: LICENSE
Requires-Dist: torch<3.0.0,>=2.0.0
Requires-Dist: transformers<4.56.0,>=4.52.0
Requires-Dist: numpy<3.0.0,>=1.24.0
Requires-Dist: pyyaml<7.0,>=6.0
Requires-Dist: json-repair<1.0.0,>=0.30.0
Requires-Dist: tqdm>=4.65.0
Provides-Extra: vllm
Requires-Dist: vllm<0.13,>=0.9.2; extra == "vllm"
Provides-Extra: reranker
Requires-Dist: FlagEmbedding>=1.0.0; extra == "reranker"
Provides-Extra: benchmark
Requires-Dist: scipy>=1.10.0; extra == "benchmark"
Requires-Dist: matplotlib>=3.7.0; extra == "benchmark"
Requires-Dist: pandas>=2.0.0; extra == "benchmark"
Requires-Dist: datasets>=2.14.0; extra == "benchmark"
Requires-Dist: pyarrow>=10.0.0; extra == "benchmark"
Provides-Extra: full
Requires-Dist: vllm<0.13,>=0.9.2; extra == "full"
Requires-Dist: FlagEmbedding>=1.0.0; extra == "full"
Provides-Extra: dev
Requires-Dist: pytest>=7.0.0; extra == "dev"
Requires-Dist: pytest-cov>=4.0.0; extra == "dev"
Requires-Dist: ruff>=0.1.0; extra == "dev"
Requires-Dist: mypy>=1.0.0; extra == "dev"
Requires-Dist: scipy>=1.10.0; extra == "dev"
Requires-Dist: matplotlib>=3.7.0; extra == "dev"
Requires-Dist: pandas>=2.0.0; extra == "dev"
Requires-Dist: datasets>=2.14.0; extra == "dev"
Provides-Extra: test
Requires-Dist: pytest>=7.0.0; extra == "test"
Requires-Dist: pytest-cov>=4.0.0; extra == "test"
Dynamic: license-file
